hrtps/__init__.py
hrtps/simer.py
hrtps/data/meanful/vocab.txt
hrtps/data/oral_preprocess/aux_word.txt
hrtps/data/oral_preprocess/modal_word.txt
hrtps/data/overtalk/vocab.txt
hrtps/data/rule_subject/subject_regexp.txt
hrtps/data/starclf/model_info.json
hrtps/data/starclf/action/model_info.json
hrtps/data/starclf/result/model_info.json
hrtps/data/starclf/situation/model_info.json
hrtps/data/starner/action/model_info.json
hrtps/data/starner/result/model_info.json
hrtps/data/starner/situation/model_info.json
hrtps/data/subsen/mask_model_info.json
hrtps/data/subsen/model_info.json
hrtps/kashgari/process.py
hrtps/meanful/__init__.py
hrtps/nvwa/__init__.py
hrtps/oral_preprocess/__init__.py
hrtps/oral_preprocess/preprocess.py
hrtps/overtalk/__init__.py
hrtps/overtalk/over.py
hrtps/star/__init__.py
hrtps/star/rule_subject_ex.py
hrtps/star/thriftio/STARService.py
hrtps/star/thriftio/__init__.py
hrtps/star/thriftio/constants.py
hrtps/star/thriftio/ttypes.py
hrtps/utils/__init__.py
hrtps/utils/logutil.py
hrtps/utils/text_utils.py
hrtps/utils/tokenization.py
hrtps/vad/__init__.py
hrtpsnlpsdk-0.2.12.dist-info/METADATA
hrtpsnlpsdk-0.2.12.dist-info/WHEEL
hrtpsnlpsdk-0.2.12.dist-info/top_level.txt
hrtpsnlpsdk-0.2.12.dist-info/RECORD
