Metadata-Version: 2.1
Name: hrtpsnlpsdk
Version: 0.2.12
Summary: hrtps nlp util package
Home-page: UNKNOWN
Author: haozy@hrtps.com
Author-email: haozy@hrtps.com
License: UNKNOWN
Platform: UNKNOWN
Requires-Python: >=3.6
Requires-Dist: requests
Requires-Dist: thrift
